stedsans/__init__.py
stedsans/stedsans.py
stedsans/data/KOMMUNE.csv
stedsans/data/KOMMUNE.dbf
stedsans/data/KOMMUNE.prj
stedsans/data/KOMMUNE.shp
stedsans/data/KOMMUNE.shx
stedsans/data/__init__.py
stedsans/data/aarhus_example.txt
stedsans/data/jylland_example.txt
stedsans/data/load_data.py
stedsans/geography/__init__.py
stedsans/geography/geography.py
stedsans/nlp/__init__.py
stedsans/nlp/ner/__init__.py
stedsans/nlp/ner/download_models.py
stedsans/nlp/ner/entity_extractor.py
stedsans/nlp/ner/model.py
stedsans/nlp/ner/predict.py
stedsans/utils/__init__.py
stedsans/utils/core.py
stedsans/utils/geo_utils.py
stedsans/utils/nlp_utils.py
stedsans-0.0.12.dist-info/LICENSE
stedsans-0.0.12.dist-info/METADATA
stedsans-0.0.12.dist-info/WHEEL
stedsans-0.0.12.dist-info/top_level.txt
stedsans-0.0.12.dist-info/RECORD
