Metadata-Version: 2.1
Name: stedsans
Version: 0.0.12
Summary: stedsans is a package capable of doing geospatial analyses from text.
Home-page: https://github.com/maltehb/stedsans
Author: Malte Højmark-Bertelsen, Jakob Grøhn Damgaard
Author-email: hjb@kmd.dk, bokajgd@gmail.com
License: UNKNOWN
Keywords: Geospatial Analysis NLP Danish English
Platform: UNKNOWN
Classifier: Development Status :: 4 - Beta
Classifier: Intended Audience :: Science/Research
Classifier: Topic :: Scientific/Engineering
Classifier: Programming Language :: Python :: 3
Classifier: License :: OSI Approved :: Apache Software License
Classifier: Operating System :: OS Independent
Requires-Python: >=3.7
License-File: LICENSE
Requires-Dist: numpy (==1.20.1)
Requires-Dist: pandas (==1.2.2)
Requires-Dist: transformers (==4.4.2)
Requires-Dist: nltk (==3.5)
Requires-Dist: geopy (==2.1.0)
Requires-Dist: folium (==0.12.1)
Requires-Dist: torch (==1.7.1)
Requires-Dist: flake8 (==3.8.4)
Requires-Dist: parameterized (==0.8.1)
Requires-Dist: matplotlib (==3.1.3)
Requires-Dist: pointpats (==2.2.0)
Requires-Dist: descartes (==1.1.0)
Requires-Dist: importlib-resources (==5.1.4)
